cvelib/__init__.py
cvelib/cli.py
cvelib/cve_api.py
cvelib/schemas/CVE_JSON_adpContainer_5.1.1.json
cvelib/schemas/CVE_JSON_bundled_5.1.1.json
cvelib/schemas/CVE_JSON_cnaPublishedContainer_5.1.1.json
cvelib/schemas/CVE_JSON_cnaRejectedContainer_5.1.1.json
cvelib/schemas/README.md
cvelib/schemas/extract_container_schemas.py
cvelib-1.8.0.dist-info/METADATA
cvelib-1.8.0.dist-info/WHEEL
cvelib-1.8.0.dist-info/entry_points.txt
cvelib-1.8.0.dist-info/licenses/LICENSE
cvelib-1.8.0.dist-info/RECORD
