Metadata-Version: 2.4
Name: cvelib
Version: 1.8.0
Summary: A library and command line interface for the CVE Project services.
Project-URL: Homepage, https://github.com/RedHatProductSecurity/cvelib
Project-URL: Repository, https://github.com/RedHatProductSecurity/cvelib
Author-email: Red Hat Product Security <secalert@redhat.com>
License-Expression: MIT
License-File: LICENSE
Classifier: License :: OSI Approved :: MIT License
Classifier: Programming Language :: Python :: 3
Classifier: Programming Language :: Python :: 3.9
Classifier: Programming Language :: Python :: 3.10
Classifier: Programming Language :: Python :: 3.11
Classifier: Programming Language :: Python :: 3.12
Classifier: Programming Language :: Python :: 3.13
Classifier: Topic :: Security
Requires-Python: >=3.9
Requires-Dist: click>=7.1.2
Requires-Dist: jsonschema>=4.7.2
Requires-Dist: requests>=2.32.0
Provides-Extra: dev
Requires-Dist: click-man; extra == 'dev'
Requires-Dist: mypy; extra == 'dev'
Requires-Dist: pytest; extra == 'dev'
Requires-Dist: ruff; extra == 'dev'
Requires-Dist: tox; extra == 'dev'
Requires-Dist: types-click; extra == 'dev'
Requires-Dist: types-jsonschema; extra == 'dev'
Requires-Dist: types-requests; extra == 'dev'
Provides-Extra: test
Requires-Dist: pytest; extra == 'test'
